LICENSE
MANIFEST.in
README.md
package.json
setup.py
dapitokc/__init__.py
dapitokc/_imports_.py
dapitokc/dapitokc.min.js
dapitokc/dapitokc.min.js.map
dapitokc/dashapitokenconsumer.py
dapitokc/metadata.json
dapitokc/package-info.json
dapitokc.egg-info/PKG-INFO
dapitokc.egg-info/SOURCES.txt
dapitokc.egg-info/dependency_links.txt
dapitokc.egg-info/top_level.txt