Metadata-Version: 1.1
Name: dapitokc
Version: 0.0.3
Summary: Passes a token from any browser to dash server
Home-page: UNKNOWN
Author: rdanb <razvan.birle@gmail.com>
Author-email: UNKNOWN
License: MIT
Platform: UNKNOWN
Classifier: Framework :: Dash
